{"nm":"Composição 1","ddd":0,"h":400,"w":400,"meta":{"g":"@lottiefiles/toolkit-js 0.26.1"},"layers":[{"ty":0,"nm":"radar","sr":1,"st":0,"op":270,"ip":0,"hd":false,"ddd":0,"bm":0,"hasMask":false,"ao":0,"ks":{"a":{"a":0,"k":[50,50,0],"ix":1},"s":{"a":0,"k":[100,100,100],"ix":6},"sk":{"a":0,"k":0},"p":{"a":0,"k":[200.838,201.053,0],"ix":2},"r":{"a":0,"k":0,"ix":10},"sa":{"a":0,"k":0},"o":{"a":0,"k":100,"ix":11}},"ef":[],"w":100,"h":100,"refId":"comp_0","ind":1},{"ty":0,"nm":"searching","sr":1,"st":0,"op":270,"ip":0,"hd":false,"ddd":0,"bm":0,"hasMask":false,"ao":0,"ks":{"a":{"a":0,"k":[200,200,0],"ix":1},"s":{"a":0,"k":[100,100,100],"ix":6},"sk":{"a":0,"k":0},"p":{"a":0,"k":[200,200,0],"ix":2},"r":{"a":0,"k":0,"ix":10},"sa":{"a":0,"k":0},"o":{"a":0,"k":100,"ix":11}},"ef":[],"w":400,"h":400,"refId":"comp_1","ind":2}],"v":"4.11.0","fr":30,"op":270,"ip":0,"assets":[{"nm":"","id":"comp_0","layers":[{"ty":4,"nm":"radar","sr":1,"st":0,"op":322,"ip":0,"hd":false,"ddd":0,"bm":0,"hasMask":false,"ao":0,"ks":{"a":{"a":0,"k":[1.612,-3.115,0],"ix":1},"s":{"a":0,"k":[494,494,100],"ix":6},"sk":{"a":0,"k":0},"p":{"a":0,"k":[50.362,48.885,0],"ix":2},"r":{"a":0,"k":0,"ix":10},"sa":{"a":0,"k":0},"o":{"a":0,"k":100,"ix":11}},"ef":[],"shapes":[{"ty":"gr","bm":0,"hd":false,"mn":"ADBE Vector Group","nm":"Elipse verde","ix":1,"cix":2,"np":3,"it":[{"ty":"sh","bm":0,"hd":false,"mn":"ADBE Vector Shape - Group","nm":"Caminho 1","ix":1,"d":1,"ks":{"a":0,"k":{"c":true,"i":[[3.944,0],[0,-3.944],[-3.944,0],[0,3.944]],"o":[[-3.944,0],[0,3.944],[3.944,0],[0,-3.944]],"v":[[0,-7.142],[-7.142,0],[0,7.142],[7.142,0]]},"ix":2}},{"ty":"fl","bm":0,"hd":false,"mn":"ADBE Vector Graphic - Fill","nm":"Preenchimento 1","c":{"a":0,"k":[0.0078,0.9137,0.9961],"ix":4},"r":1,"o":{"a":0,"k":100,"ix":5}},{"ty":"tr","a":{"a":0,"k":[0,0],"ix":1},"s":{"a":1,"k":[{"o":{"x":0.333,"y":0},"i":{"x":0,"y":1},"s":[0,0],"t":10},{"o":{"x":0.167,"y":0},"i":{"x":0.815,"y":0.883},"s":[79.235,79.235],"t":20},{"o":{"x":0.748,"y":0.011},"i":{"x":0.43,"y":1},"s":[79.235,79.235],"t":240},{"s":[0,0],"t":250}],"ix":3},"sk":{"a":0,"k":0,"ix":4},"p":{"a":0,"k":[1.612,-3.115],"ix":2},"r":{"a":0,"k":0,"ix":6},"sa":{"a":0,"k":0,"ix":5},"o":{"a":0,"k":100,"ix":7}}]},{"ty":"gr","bm":0,"hd":false,"mn":"ADBE Vector Group","nm":"Elipse branca","ix":2,"cix":2,"np":3,"it":[{"ty":"sh","bm":0,"hd":false,"mn":"ADBE Vector Shape - Group","nm":"Caminho 1","ix":1,"d":1,"ks":{"a":0,"k":{"c":true,"i":[[3.944,0],[0,-3.944],[-3.944,0],[0,3.944]],"o":[[-3.944,0],[0,3.944],[3.944,0],[0,-3.944]],"v":[[0,-7.142],[-7.142,0],[0,7.142],[7.142,0]]},"ix":2}},{"ty":"fl","bm":0,"hd":false,"mn":"ADBE Vector Graphic - Fill","nm":"Preenchimento 1","c":{"a":0,"k":[0.2902,0.2627,0.9255],"ix":4},"r":1,"o":{"a":0,"k":100,"ix":5}},{"ty":"tr","a":{"a":0,"k":[0,0],"ix":1},"s":{"a":1,"k":[{"o":{"x":0.396,"y":-0.004},"i":{"x":0.085,"y":0.999},"s":[0,0],"t":0},{"o":{"x":0.167,"y":0},"i":{"x":0.815,"y":0.61},"s":[100,100],"t":15},{"o":{"x":0.858,"y":0.01},"i":{"x":0.548,"y":1},"s":[100,100],"t":245},{"s":[0,0],"t":260}],"ix":3},"sk":{"a":0,"k":0,"ix":4},"p":{"a":0,"k":[1.612,-3.115],"ix":2},"r":{"a":0,"k":0,"ix":6},"sa":{"a":0,"k":0,"ix":5},"o":{"a":0,"k":100,"ix":7}}]}],"ind":1}]},{"nm":"","id":"comp_1","layers":[{"ty":4,"nm":"Camada de forma 8","sr":1,"st":165,"op":300,"ip":165,"hd":false,"ddd":0,"bm":0,"hasMask":false,"ao":0,"ks":{"a":{"a":0,"k":[0.838,5.053,0],"ix":1},"s":{"a":1,"k":[{"o":{"x":0.333,"y":0},"i":{"x":0.667,"y":1},"s":[0,0,100],"t":165},{"s":[118.32,118.32,100],"t":233}],"ix":6},"sk":{"a":0,"k":0},"p":{"a":0,"k":[200.838,201.053,0],"ix":2},"r":{"a":0,"k":0,"ix":10},"sa":{"a":0,"k":0},"o":{"a":1,"k":[{"o":{"x":0.333,"y":0},"i":{"x":0.667,"y":1},"s":[15],"t":165},{"o":{"x":0.167,"y":0},"i":{"x":0.833,"y":1},"s":[40],"t":203},{"s":[0],"t":233}],"ix":11}},"ef":[],"shapes":[{"ty":"gr","bm":0,"hd":false,"mn":"ADBE Vector Group","nm":"Elipse 1","ix":1,"cix":2,"np":3,"it":[{"ty":"el","bm":0,"hd":false,"mn":"ADBE Vector Shape - Ellipse","nm":"Caminho da elipse 1","d":1,"p":{"a":0,"k":[0,0],"ix":3},"s":{"a":0,"k":[316.59,316.59],"ix":2}},{"ty":"st","bm":0,"hd":false,"mn":"ADBE Vector Graphic - Stroke","nm":"Traçado 1","lc":1,"lj":1,"ml":4,"o":{"a":0,"k":100,"ix":4},"w":{"a":0,"k":1,"ix":5},"c":{"a":0,"k":[0.0078,0.9137,0.9961],"ix":3}},{"ty":"tr","a":{"a":0,"k":[0,0],"ix":1},"s":{"a":0,"k":[100,100],"ix":3},"sk":{"a":0,"k":0,"ix":4},"p":{"a":0,"k":[0.838,5.053],"ix":2},"r":{"a":0,"k":0,"ix":6},"sa":{"a":0,"k":0,"ix":5},"o":{"a":0,"k":100,"ix":7}}]}],"ind":1},{"ty":4,"nm":"Camada de forma 7","sr":1,"st":155,"op":300,"ip":155,"hd":false,"ddd":0,"bm":0,"hasMask":false,"ao":0,"ks":{"a":{"a":0,"k":[0.838,5.053,0],"ix":1},"s":{"a":1,"k":[{"o":{"x":0.333,"y":0},"i":{"x":0.667,"y":1},"s":[0,0,100],"t":155},{"s":[118.32,118.32,100],"t":223}],"ix":6},"sk":{"a":0,"k":0},"p":{"a":0,"k":[200.838,201.053,0],"ix":2},"r":{"a":0,"k":0,"ix":10},"sa":{"a":0,"k":0},"o":{"a":1,"k":[{"o":{"x":0.333,"y":0},"i":{"x":0.667,"y":1},"s":[15],"t":155},{"o":{"x":0.167,"y":0},"i":{"x":0.833,"y":1},"s":[40],"t":193},{"s":[0],"t":223}],"ix":11}},"ef":[],"shapes":[{"ty":"gr","bm":0,"hd":false,"mn":"ADBE Vector Group","nm":"Elipse 1","ix":1,"cix":2,"np":3,"it":[{"ty":"el","bm":0,"hd":false,"mn":"ADBE Vector Shape - Ellipse","nm":"Caminho da elipse 1","d":1,"p":{"a":0,"k":[0,0],"ix":3},"s":{"a":0,"k":[316.59,316.59],"ix":2}},{"ty":"st","bm":0,"hd":false,"mn":"ADBE Vector Graphic - Stroke","nm":"Traçado 1","lc":1,"lj":1,"ml":4,"o":{"a":0,"k":100,"ix":4},"w":{"a":0,"k":1,"ix":5},"c":{"a":0,"k":[0.2902,0.2627,0.9255],"ix":3}},{"ty":"tr","a":{"a":0,"k":[0,0],"ix":1},"s":{"a":0,"k":[100,100],"ix":3},"sk":{"a":0,"k":0,"ix":4},"p":{"a":0,"k":[0.838,5.053],"ix":2},"r":{"a":0,"k":0,"ix":6},"sa":{"a":0,"k":0,"ix":5},"o":{"a":0,"k":100,"ix":7}}]}],"ind":2},{"ty":4,"nm":"Camada de forma 6","sr":1,"st":145,"op":300,"ip":145,"hd":false,"ddd":0,"bm":0,"hasMask":false,"ao":0,"ks":{"a":{"a":0,"k":[0.838,5.053,0],"ix":1},"s":{"a":1,"k":[{"o":{"x":0.333,"y":0},"i":{"x":0.667,"y":1},"s":[0,0,100],"t":145},{"s":[118.32,118.32,100],"t":213}],"ix":6},"sk":{"a":0,"k":0},"p":{"a":0,"k":[200.838,201.053,0],"ix":2},"r":{"a":0,"k":0,"ix":10},"sa":{"a":0,"k":0},"o":{"a":1,"k":[{"o":{"x":0.333,"y":0},"i":{"x":0.667,"y":1},"s":[15],"t":145},{"o":{"x":0.167,"y":0},"i":{"x":0.833,"y":1},"s":[40],"t":183},{"s":[0],"t":213}],"ix":11}},"ef":[],"shapes":[{"ty":"gr","bm":0,"hd":false,"mn":"ADBE Vector Group","nm":"Elipse 1","ix":1,"cix":2,"np":3,"it":[{"ty":"el","bm":0,"hd":false,"mn":"ADBE Vector Shape - Ellipse","nm":"Caminho da elipse 1","d":1,"p":{"a":0,"k":[0,0],"ix":3},"s":{"a":0,"k":[316.59,316.59],"ix":2}},{"ty":"st","bm":0,"hd":false,"mn":"ADBE Vector Graphic - Stroke","nm":"Traçado 1","lc":1,"lj":1,"ml":4,"o":{"a":0,"k":100,"ix":4},"w":{"a":0,"k":1,"ix":5},"c":{"a":0,"k":[0.0078,0.9137,0.9961],"ix":3}},{"ty":"tr","a":{"a":0,"k":[0,0],"ix":1},"s":{"a":0,"k":[100,100],"ix":3},"sk":{"a":0,"k":0,"ix":4},"p":{"a":0,"k":[0.838,5.053],"ix":2},"r":{"a":0,"k":0,"ix":6},"sa":{"a":0,"k":0,"ix":5},"o":{"a":0,"k":100,"ix":7}}]}],"ind":3},{"ty":4,"nm":"Camada de forma 5","sr":1,"st":135,"op":300,"ip":135,"hd":false,"ddd":0,"bm":0,"hasMask":false,"ao":0,"ks":{"a":{"a":0,"k":[0.838,5.053,0],"ix":1},"s":{"a":1,"k":[{"o":{"x":0.333,"y":0},"i":{"x":0.667,"y":1},"s":[0,0,100],"t":135},{"s":[118.32,118.32,100],"t":203}],"ix":6},"sk":{"a":0,"k":0},"p":{"a":0,"k":[200.838,201.053,0],"ix":2},"r":{"a":0,"k":0,"ix":10},"sa":{"a":0,"k":0},"o":{"a":1,"k":[{"o":{"x":0.333,"y":0},"i":{"x":0.667,"y":1},"s":[15],"t":135},{"o":{"x":0.167,"y":0},"i":{"x":0.833,"y":1},"s":[40],"t":173},{"s":[0],"t":203}],"ix":11}},"ef":[],"shapes":[{"ty":"gr","bm":0,"hd":false,"mn":"ADBE Vector Group","nm":"Elipse 1","ix":1,"cix":2,"np":3,"it":[{"ty":"el","bm":0,"hd":false,"mn":"ADBE Vector Shape - Ellipse","nm":"Caminho da elipse 1","d":1,"p":{"a":0,"k":[0,0],"ix":3},"s":{"a":0,"k":[316.59,316.59],"ix":2}},{"ty":"st","bm":0,"hd":false,"mn":"ADBE Vector Graphic - Stroke","nm":"Traçado 1","lc":1,"lj":1,"ml":4,"o":{"a":0,"k":100,"ix":4},"w":{"a":0,"k":1,"ix":5},"c":{"a":0,"k":[0.2902,0.2627,0.9255],"ix":3}},{"ty":"tr","a":{"a":0,"k":[0,0],"ix":1},"s":{"a":0,"k":[100,100],"ix":3},"sk":{"a":0,"k":0,"ix":4},"p":{"a":0,"k":[0.838,5.053],"ix":2},"r":{"a":0,"k":0,"ix":6},"sa":{"a":0,"k":0,"ix":5},"o":{"a":0,"k":100,"ix":7}}]}],"ind":4},{"ty":4,"nm":"Camada de forma 4","sr":1,"st":67,"op":287,"ip":67,"hd":false,"ddd":0,"bm":0,"hasMask":false,"ao":0,"ks":{"a":{"a":0,"k":[0.838,5.053,0],"ix":1},"s":{"a":1,"k":[{"o":{"x":0.333,"y":0},"i":{"x":0.667,"y":1},"s":[0,0,100],"t":67},{"s":[118.32,118.32,100],"t":135}],"ix":6},"sk":{"a":0,"k":0},"p":{"a":0,"k":[200.838,201.053,0],"ix":2},"r":{"a":0,"k":0,"ix":10},"sa":{"a":0,"k":0},"o":{"a":1,"k":[{"o":{"x":0.333,"y":0},"i":{"x":0.667,"y":1},"s":[15],"t":67},{"o":{"x":0.167,"y":0},"i":{"x":0.833,"y":1},"s":[40],"t":105},{"s":[0],"t":135}],"ix":11}},"ef":[],"shapes":[{"ty":"gr","bm":0,"hd":false,"mn":"ADBE Vector Group","nm":"Elipse 1","ix":1,"cix":2,"np":3,"it":[{"ty":"el","bm":0,"hd":false,"mn":"ADBE Vector Shape - Ellipse","nm":"Caminho da elipse 1","d":1,"p":{"a":0,"k":[0,0],"ix":3},"s":{"a":0,"k":[316.59,316.59],"ix":2}},{"ty":"st","bm":0,"hd":false,"mn":"ADBE Vector Graphic - Stroke","nm":"Traçado 1","lc":1,"lj":1,"ml":4,"o":{"a":0,"k":100,"ix":4},"w":{"a":0,"k":1,"ix":5},"c":{"a":0,"k":[0.0078,0.9137,0.9961],"ix":3}},{"ty":"tr","a":{"a":0,"k":[0,0],"ix":1},"s":{"a":0,"k":[100,100],"ix":3},"sk":{"a":0,"k":0,"ix":4},"p":{"a":0,"k":[0.838,5.053],"ix":2},"r":{"a":0,"k":0,"ix":6},"sa":{"a":0,"k":0,"ix":5},"o":{"a":0,"k":100,"ix":7}}]}],"ind":5},{"ty":4,"nm":"Camada de forma 3","sr":1,"st":57,"op":277,"ip":57,"hd":false,"ddd":0,"bm":0,"hasMask":false,"ao":0,"ks":{"a":{"a":0,"k":[0.838,5.053,0],"ix":1},"s":{"a":1,"k":[{"o":{"x":0.333,"y":0},"i":{"x":0.667,"y":1},"s":[0,0,100],"t":57},{"s":[118.32,118.32,100],"t":125}],"ix":6},"sk":{"a":0,"k":0},"p":{"a":0,"k":[200.838,201.053,0],"ix":2},"r":{"a":0,"k":0,"ix":10},"sa":{"a":0,"k":0},"o":{"a":1,"k":[{"o":{"x":0.333,"y":0},"i":{"x":0.667,"y":1},"s":[15],"t":57},{"o":{"x":0.167,"y":0},"i":{"x":0.833,"y":1},"s":[40],"t":95},{"s":[0],"t":125}],"ix":11}},"ef":[],"shapes":[{"ty":"gr","bm":0,"hd":false,"mn":"ADBE Vector Group","nm":"Elipse 1","ix":1,"cix":2,"np":3,"it":[{"ty":"el","bm":0,"hd":false,"mn":"ADBE Vector Shape - Ellipse","nm":"Caminho da elipse 1","d":1,"p":{"a":0,"k":[0,0],"ix":3},"s":{"a":0,"k":[316.59,316.59],"ix":2}},{"ty":"st","bm":0,"hd":false,"mn":"ADBE Vector Graphic - Stroke","nm":"Traçado 1","lc":1,"lj":1,"ml":4,"o":{"a":0,"k":100,"ix":4},"w":{"a":0,"k":1,"ix":5},"c":{"a":0,"k":[0.2902,0.2627,0.9255],"ix":3}},{"ty":"tr","a":{"a":0,"k":[0,0],"ix":1},"s":{"a":0,"k":[100,100],"ix":3},"sk":{"a":0,"k":0,"ix":4},"p":{"a":0,"k":[0.838,5.053],"ix":2},"r":{"a":0,"k":0,"ix":6},"sa":{"a":0,"k":0,"ix":5},"o":{"a":0,"k":100,"ix":7}}]}],"ind":6},{"ty":4,"nm":"Camada de forma 2","sr":1,"st":47,"op":267,"ip":47,"hd":false,"ddd":0,"bm":0,"hasMask":false,"ao":0,"ks":{"a":{"a":0,"k":[0.838,5.053,0],"ix":1},"s":{"a":1,"k":[{"o":{"x":0.333,"y":0},"i":{"x":0.667,"y":1},"s":[0,0,100],"t":47},{"s":[118.32,118.32,100],"t":115}],"ix":6},"sk":{"a":0,"k":0},"p":{"a":0,"k":[200.838,201.053,0],"ix":2},"r":{"a":0,"k":0,"ix":10},"sa":{"a":0,"k":0},"o":{"a":1,"k":[{"o":{"x":0.333,"y":0},"i":{"x":0.667,"y":1},"s":[15],"t":47},{"o":{"x":0.167,"y":0},"i":{"x":0.833,"y":1},"s":[40],"t":85},{"s":[0],"t":115}],"ix":11}},"ef":[],"shapes":[{"ty":"gr","bm":0,"hd":false,"mn":"ADBE Vector Group","nm":"Elipse 1","ix":1,"cix":2,"np":3,"it":[{"ty":"el","bm":0,"hd":false,"mn":"ADBE Vector Shape - Ellipse","nm":"Caminho da elipse 1","d":1,"p":{"a":0,"k":[0,0],"ix":3},"s":{"a":0,"k":[316.59,316.59],"ix":2}},{"ty":"st","bm":0,"hd":false,"mn":"ADBE Vector Graphic - Stroke","nm":"Traçado 1","lc":1,"lj":1,"ml":4,"o":{"a":0,"k":100,"ix":4},"w":{"a":0,"k":1,"ix":5},"c":{"a":0,"k":[0.0078,0.9137,0.9961],"ix":3}},{"ty":"tr","a":{"a":0,"k":[0,0],"ix":1},"s":{"a":0,"k":[100,100],"ix":3},"sk":{"a":0,"k":0,"ix":4},"p":{"a":0,"k":[0.838,5.053],"ix":2},"r":{"a":0,"k":0,"ix":6},"sa":{"a":0,"k":0,"ix":5},"o":{"a":0,"k":100,"ix":7}}]}],"ind":7},{"ty":4,"nm":"Camada de forma 1","sr":1,"st":37,"op":257,"ip":37,"hd":false,"ddd":0,"bm":0,"hasMask":false,"ao":0,"ks":{"a":{"a":0,"k":[0.838,5.053,0],"ix":1},"s":{"a":1,"k":[{"o":{"x":0.333,"y":0},"i":{"x":0.667,"y":1},"s":[0,0,100],"t":37},{"s":[118.32,118.32,100],"t":105}],"ix":6},"sk":{"a":0,"k":0},"p":{"a":0,"k":[200.838,201.053,0],"ix":2},"r":{"a":0,"k":0,"ix":10},"sa":{"a":0,"k":0},"o":{"a":1,"k":[{"o":{"x":0.333,"y":0},"i":{"x":0.667,"y":1},"s":[15],"t":37},{"o":{"x":0.167,"y":0},"i":{"x":0.833,"y":1},"s":[40],"t":75},{"s":[0],"t":105}],"ix":11}},"ef":[],"shapes":[{"ty":"gr","bm":0,"hd":false,"mn":"ADBE Vector Group","nm":"Elipse 1","ix":1,"cix":2,"np":3,"it":[{"ty":"el","bm":0,"hd":false,"mn":"ADBE Vector Shape - Ellipse","nm":"Caminho da elipse 1","d":1,"p":{"a":0,"k":[0,0],"ix":3},"s":{"a":0,"k":[316.59,316.59],"ix":2}},{"ty":"st","bm":0,"hd":false,"mn":"ADBE Vector Graphic - Stroke","nm":"Traçado 1","lc":1,"lj":1,"ml":4,"o":{"a":0,"k":100,"ix":4},"w":{"a":0,"k":1,"ix":5},"c":{"a":0,"k":[0.2902,0.2627,0.9255],"ix":3}},{"ty":"tr","a":{"a":0,"k":[0,0],"ix":1},"s":{"a":0,"k":[100,100],"ix":3},"sk":{"a":0,"k":0,"ix":4},"p":{"a":0,"k":[0.838,5.053],"ix":2},"r":{"a":0,"k":0,"ix":6},"sa":{"a":0,"k":0,"ix":5},"o":{"a":0,"k":100,"ix":7}}]}],"ind":8}]}]}